{"nodes": [{"id": "staff_app_design_spec", "label": "PowerNet Staff App (Flutter) Design Spec", "file_type": "document", "source_file": "docs/superpowers/specs/2026-04-25-powernet-staff-app-design.md", "source_location": null, "source_url": null, "captured_at": "2026-04-25", "author": null, "contributor": null}, {"id": "staff_app_flutter_app", "label": "PowerNet Staff Flutter App", "file_type": "rationale", "source_file": "docs/superpowers/specs/2026-04-25-powernet-staff-app-design.md", "source_location": null, "source_url": null, "captured_at": null, "author": null, "contributor": null}, {"id": "staff_app_verify_staff_login_rpc", "label": "verify_staff_login RPC", "file_type": "rationale", "source_file": "docs/superpowers/specs/2026-04-25-powernet-staff-app-design.md", "source_location": null, "source_url": null, "captured_at": null, "author": null, "contributor": null}, {"id": "staff_app_auth_provider", "label": "AuthProvider (Flutter ChangeNotifier)", "file_type": "rationale", "source_file": "docs/superpowers/specs/2026-04-25-powernet-staff-app-design.md", "source_location": null, "source_url": null, "captured_at": null, "author": null, "contributor": null}, {"id": "staff_app_shared_preferences", "label": "SharedPreferences Session Persistence", "file_type": "rationale", "source_file": "docs/superpowers/specs/2026-04-25-powernet-staff-app-design.md", "source_location": null, "source_url": null, "captured_at": null, "author": null, "contributor": null}, {"id": "staff_app_splash_screen", "label": "SplashScreen (Flutter)", "file_type": "rationale", "source_file": "docs/superpowers/specs/2026-04-25-powernet-staff-app-design.md", "source_location": null, "source_url": null, "captured_at": null, "author": null, "contributor": null}, {"id": "staff_app_home_screen", "label": "HomeScreen (Flutter Welcome + Role Display)", "file_type": "rationale", "source_file": "docs/superpowers/specs/2026-04-25-powernet-staff-app-design.md", "source_location": null, "source_url": null, "captured_at": null, "author": null, "contributor": null}, {"id": "staff_app_staff_model", "label": "Staff Model (Flutter Dart)", "file_type": "rationale", "source_file": "docs/superpowers/specs/2026-04-25-powernet-staff-app-design.md", "source_location": null, "source_url": null, "captured_at": null, "author": null, "contributor": null}], "edges": [{"source": "staff_app_design_spec", "target": "staff_app_flutter_app", "relation": "references", "confidence": "EXTRACTED", "confidence_score": 1.0, "source_file": "docs/superpowers/specs/2026-04-25-powernet-staff-app-design.md", "source_location": null, "weight": 1.0}, {"source": "staff_app_design_spec", "target": "staff_app_verify_staff_login_rpc", "relation": "references", "confidence": "EXTRACTED", "confidence_score": 1.0, "source_file": "docs/superpowers/specs/2026-04-25-powernet-staff-app-design.md", "source_location": null, "weight": 1.0}, {"source": "staff_app_design_spec", "target": "staff_app_auth_provider", "relation": "references", "confidence": "EXTRACTED", "confidence_score": 1.0, "source_file": "docs/superpowers/specs/2026-04-25-powernet-staff-app-design.md", "source_location": null, "weight": 1.0}, {"source": "staff_app_design_spec", "target": "staff_app_shared_preferences", "relation": "references", "confidence": "EXTRACTED", "confidence_score": 1.0, "source_file": "docs/superpowers/specs/2026-04-25-powernet-staff-app-design.md", "source_location": null, "weight": 1.0}, {"source": "staff_app_design_spec", "target": "staff_app_splash_screen", "relation": "references", "confidence": "EXTRACTED", "confidence_score": 1.0, "source_file": "docs/superpowers/specs/2026-04-25-powernet-staff-app-design.md", "source_location": null, "weight": 1.0}, {"source": "staff_app_design_spec", "target": "staff_app_home_screen", "relation": "references", "confidence": "EXTRACTED", "confidence_score": 1.0, "source_file": "docs/superpowers/specs/2026-04-25-powernet-staff-app-design.md", "source_location": null, "weight": 1.0}, {"source": "staff_app_design_spec", "target": "staff_app_staff_model", "relation": "references", "confidence": "EXTRACTED", "confidence_score": 1.0, "source_file": "docs/superpowers/specs/2026-04-25-powernet-staff-app-design.md", "source_location": null, "weight": 1.0}, {"source": "staff_app_auth_provider", "target": "staff_app_shared_preferences", "relation": "implements", "confidence": "EXTRACTED", "confidence_score": 1.0, "source_file": "docs/superpowers/specs/2026-04-25-powernet-staff-app-design.md", "source_location": null, "weight": 1.0}, {"source": "staff_app_auth_provider", "target": "staff_app_verify_staff_login_rpc", "relation": "calls", "confidence": "EXTRACTED", "confidence_score": 1.0, "source_file": "docs/superpowers/specs/2026-04-25-powernet-staff-app-design.md", "source_location": null, "weight": 1.0}, {"source": "staff_app_splash_screen", "target": "staff_app_shared_preferences", "relation": "calls", "confidence": "EXTRACTED", "confidence_score": 1.0, "source_file": "docs/superpowers/specs/2026-04-25-powernet-staff-app-design.md", "source_location": null, "weight": 1.0}, {"source": "staff_app_splash_screen", "target": "staff_app_home_screen", "relation": "references", "confidence": "EXTRACTED", "confidence_score": 1.0, "source_file": "docs/superpowers/specs/2026-04-25-powernet-staff-app-design.md", "source_location": null, "weight": 1.0}, {"source": "staff_app_flutter_app", "target": "dashboard_auth_staff_table", "relation": "shares_data_with", "confidence": "EXTRACTED", "confidence_score": 1.0, "source_file": "docs/superpowers/specs/2026-04-25-powernet-staff-app-design.md", "source_location": null, "weight": 1.0}, {"source": "staff_app_flutter_app", "target": "staff_app_verify_staff_login_rpc", "relation": "calls", "confidence": "EXTRACTED", "confidence_score": 1.0, "source_file": "docs/superpowers/specs/2026-04-25-powernet-staff-app-design.md", "source_location": null, "weight": 1.0}], "hyperedges": [{"id": "staff_app_auth_flow", "label": "Flutter Staff App Authentication Flow", "nodes": ["staff_app_splash_screen", "staff_app_auth_provider", "staff_app_verify_staff_login_rpc", "staff_app_shared_preferences", "staff_app_home_screen"], "relation": "implement", "confidence": "EXTRACTED", "confidence_score": 1.0, "source_file": "docs/superpowers/specs/2026-04-25-powernet-staff-app-design.md"}]}